Mega_Bank/OOPS_Prac.py
Mega_Bank/__init__.py
Mega_Bank-0.1.dist-info/License.txt
Mega_Bank-0.1.dist-info/METADATA
Mega_Bank-0.1.dist-info/WHEEL
Mega_Bank-0.1.dist-info/top_level.txt
Mega_Bank-0.1.dist-info/RECORD
