Metadata-Version: 2.1
Name: Mega-Bank
Version: 0.1
Summary: Class package to help us create classes Accounts, Saving Account and Current Account
Author: Minautee
Author-email: minautee.m@fractal.ai
License: MIT
License-File: License.txt
Requires-Dist: pandas
Requires-Dist: requests
